musicscore/LilyPondUnofficialXMLTestSuite/LillyPondUnofficialXMLTestSuite.pdf
musicscore/LilyPondUnofficialXMLTestSuite/__init__.py
musicscore/LilyPondUnofficialXMLTestSuite/test_01a_Pitches_Pitches.py
musicscore/LilyPondUnofficialXMLTestSuite/test_01a_Pitches_Pitches.xml
musicscore/LilyPondUnofficialXMLTestSuite/test_01b_Pitches_Intervals.py
musicscore/LilyPondUnofficialXMLTestSuite/test_01b_Pitches_Intervals.xml
musicscore/LilyPondUnofficialXMLTestSuite/test_01d_Pitches_Microtones.py
musicscore/LilyPondUnofficialXMLTestSuite/test_01d_Pitches_Microtones.xml
musicscore/LilyPondUnofficialXMLTestSuite/test_01e_Pitches_ParenthesizedAccidentals.py
musicscore/LilyPondUnofficialXMLTestSuite/test_01e_Pitches_ParenthesizedAccidentals.xml
musicscore/LilyPondUnofficialXMLTestSuite/test_02b_Rests_PitchedRests.py
musicscore/LilyPondUnofficialXMLTestSuite/test_02b_Rests_PitchedRests.xml
musicscore/LilyPondUnofficialXMLTestSuite/test_02c_Rests_MultiMeasureRests.py
musicscore/LilyPondUnofficialXMLTestSuite/test_02c_Rests_MultiMeasureRests.xml
musicscore/LilyPondUnofficialXMLTestSuite/test_11a_TimeSignatures.py
musicscore/LilyPondUnofficialXMLTestSuite/test_11a_TimeSignatures.xml
musicscore/LilyPondUnofficialXMLTestSuite/test_11c_TimeSignatures_CompoundSimple.py
musicscore/LilyPondUnofficialXMLTestSuite/test_11c_TimeSignatures_CompoundSimple.xml
musicscore/LilyPondUnofficialXMLTestSuite/test_11d_TimeSignatures_CompoundMultiple.py
musicscore/LilyPondUnofficialXMLTestSuite/test_11d_TimeSignatures_CompoundMultiple.xml
musicscore/LilyPondUnofficialXMLTestSuite/test_11e_TimeSignatures_CompoundMixed.py
musicscore/LilyPondUnofficialXMLTestSuite/test_11e_TimeSignatures_CompoundMixed.xml
musicscore/LilyPondUnofficialXMLTestSuite/test_11g_TimeSignatures_SingleNumber.py
musicscore/LilyPondUnofficialXMLTestSuite/test_11g_TimeSignatures_SingleNumber.xml
musicscore/LilyPondUnofficialXMLTestSuite/test_12a_Clefs.py
musicscore/LilyPondUnofficialXMLTestSuite/test_12a_Clefs.xml
musicscore-2.5.4.dist-info/LICENSE
musicscore-2.5.4.dist-info/METADATA
musicscore-2.5.4.dist-info/WHEEL
musicscore-2.5.4.dist-info/RECORD
