Metadata-Version: 2.1
Name: musicscore
Version: 2.5.4
Summary: Generating musicxml files.
Home-page: https://github.com/alexgorji/musicscore.git
License: MIT
Author: Alex Gorji
Author-email: aligorji@hotmail.com
Requires-Python: >=3.9,<3.13
Classifier: License :: OSI Approved :: MIT License
Classifier: Operating System :: OS Independent
Classifier: Programming Language :: Python :: 3
Classifier: Programming Language :: Python :: 3.9
Classifier: Programming Language :: Python :: 3.10
Classifier: Programming Language :: Python :: 3.11
Classifier: Programming Language :: Python :: 3.12
Requires-Dist: musicxml (>=1.6,<2.0)
Project-URL: Repository, https://github.com/alexgorji/musicscore.git
